uploadcare/__init__.py
uploadcare/exceptions.py
uploadcare/uploadcare.py
uploadcare-0.1.0.dist-info/WHEEL
uploadcare-0.1.0.dist-info/METADATA
uploadcare-0.1.0.dist-info/RECORD
