Metadata-Version: 2.1
Name: uploadcare
Version: 0.1.0
Summary: 
Author: Alyetama
Author-email: 56323389+Alyetama@users.noreply.github.com
Requires-Python: >=3.6,<4.0
Classifier: Programming Language :: Python :: 3
Classifier: Programming Language :: Python :: 3.10
Classifier: Programming Language :: Python :: 3.6
Classifier: Programming Language :: Python :: 3.7
Classifier: Programming Language :: Python :: 3.8
Classifier: Programming Language :: Python :: 3.9
Requires-Dist: dateparser (>=1.1.1,<2.0.0)
Requires-Dist: requests (>=2.27.1,<3.0.0)
